moderators/__init__.py
moderators/auto_model.py
moderators/cli.py
moderators/integrations/__init__.py
moderators/integrations/base.py
moderators/integrations/transformers_moderator.py
moderators/utils/__init__.py
moderators/utils/callbacks.py
moderators/utils/deps.py
moderators/utils/events.py
moderators/utils/image.py
moderators-0.1.2.dist-info/METADATA
moderators-0.1.2.dist-info/WHEEL
moderators-0.1.2.dist-info/entry_points.txt
moderators-0.1.2.dist-info/licenses/LICENSE
moderators-0.1.2.dist-info/RECORD
