Metadata-Version: 2.4
Name: moderators
Version: 0.1.2
Summary: Moderators: One package to moderate them all
Project-URL: Homepage, https://github.com/viddexa/moderators
Project-URL: Source, https://github.com/viddexa/moderators
Project-URL: Bug Reports, https://github.com/viddexa/moderators/discussions/categories/q-a
Project-URL: Changelog, https://github.com/viddexa/moderators/releases
Author: Moderators Team
License-Expression: Apache-2.0
License-File: LICENSE
Requires-Python: >=3.9
Requires-Dist: huggingface-hub>=0.22
Requires-Dist: requests
Provides-Extra: dev
Requires-Dist: docformatter; extra == 'dev'
Requires-Dist: pillow>=9.0; extra == 'dev'
Requires-Dist: pytest-xdist; extra == 'dev'
Requires-Dist: pytest>=7.0; extra == 'dev'
Requires-Dist: ruff; extra == 'dev'
Requires-Dist: torch; extra == 'dev'
Provides-Extra: transformers
Requires-Dist: transformers>=4.36; extra == 'transformers'
